{
    "minimum_nuke_version_required": 13.2,
    "version": 1,
    "category": "MENU_NAME",
    "icon": "ICON.png",
    "nodes": [
        {
            "name": "OPTIONAL",
            "filepath": "GIZMO.gizmo",
            "icon": "ICON_IN_PLUGINPATH.png",
            "shortcut": "^+R",
            "ctx": 2
        },
        {
            "name": "OPTIONAL",
            "filepath": "SCRIPT.nk",
            "icon": "../PATH/TO/ICON.png",
            "shortcut": "Ctrl+Shift+P"
        },
        {
            "name": "PDF FILENAME",
            "filepath": "../PATH/TO.pdf",
            "icon": "ICON.png"
        },
        {
            "filepath": "python_file.py"
        }
    ]
}